datafold_xdiff/__init__.py
datafold_xdiff-0.0.1.dist-info/LICENSE
datafold_xdiff-0.0.1.dist-info/METADATA
datafold_xdiff-0.0.1.dist-info/WHEEL
datafold_xdiff-0.0.1.dist-info/entry_points.txt
datafold_xdiff-0.0.1.dist-info/top_level.txt
datafold_xdiff-0.0.1.dist-info/RECORD
