Metadata-Version: 2.1
Name: datafold-xdiff
Version: 0.0.1
Summary: The datafold xdiff
Home-page: https://pypi.org/project/datafold-xdiff
Author: Datafold
Author-email: hello@datafold.com
License: UNKNOWN
Platform: UNKNOWN
Classifier: Programming Language :: Python :: 3
Classifier: Operating System :: OS Independent
Requires-Python: >=3.6
License-File: LICENSE
Provides-Extra: dev
Requires-Dist: pre-commit ; extra == 'dev'
Requires-Dist: pytest ; extra == 'dev'
Requires-Dist: pytest-pep8 ; extra == 'dev'
Requires-Dist: pytest-cov ; extra == 'dev'
